pm_remez/__init__.py
pm_remez/pm_remez.abi3.so
pm_remez-0.2.4.dist-info/METADATA
pm_remez-0.2.4.dist-info/WHEEL
pm_remez-0.2.4.dist-info/licenses/LICENSE-APACHE
pm_remez-0.2.4.dist-info/licenses/LICENSE-MIT
pm_remez-0.2.4.dist-info/RECORD
