Metadata-Version: 2.4
Name: pm_remez
Version: 0.2.4
Classifier: Programming Language :: Rust
Classifier: License :: OSI Approved :: MIT License
Classifier: License :: OSI Approved :: Apache Software License
License-File: LICENSE-APACHE
License-File: LICENSE-MIT
Summary: Parks-McClellan Remez FIR design algorithm
Home-Page: https://maia-sdr.org/
Maintainer-email: Daniel Estevez <daniel@destevez.net>
